thermal_comfort/__init__.py
thermal_comfort/_thermal_comfort.cpython-311-x86_64-linux-musl.so
thermal_comfort/models.py
thermal_comfort/py.typed
thermal_comfort/utils.py
thermal_comfort/_thermal_comfort/__init__.pyi
thermal_comfort/_thermal_comfort/thermal_comfort_mod.pyi
thermal_comfort.libs/libgcc_s-0cd532bd.so.1
thermal_comfort.libs/libgfortran-2c33b284.so.5.0.0
thermal_comfort.libs/libquadmath-bb76a5fc.so.0.0.0
thermal_comfort-1.1.5.dist-info/METADATA
thermal_comfort-1.1.5.dist-info/WHEEL
thermal_comfort-1.1.5.dist-info/RECORD
thermal_comfort-1.1.5.dist-info/licenses/LICENSE
thermal_comfort-1.1.5.dist-info/licenses/LICENSE_pet
thermal_comfort-1.1.5.dist-info/licenses/LICENSE_pythermalcomfort
thermal_comfort-1.1.5.dist-info/licenses/LICENSE_utci
